ioos_metrics/__init__.py
ioos_metrics/_version.py
ioos_metrics/ioos_metrics.py
ioos_metrics/national_platforms.py
ioos_metrics-0.7.0.dist-info/licenses/LICENSE
ioos_metrics-0.7.0.dist-info/METADATA
ioos_metrics-0.7.0.dist-info/WHEEL
ioos_metrics-0.7.0.dist-info/top_level.txt
ioos_metrics-0.7.0.dist-info/RECORD
