Metadata-Version: 2.4
Name: ioos_metrics
Version: 0.7.0
Summary: Package to fetch various metrics for IOOS by the numbers
Maintainer: Filipe Fernandes
License: MIT License
Project-URL: documentation, https://ioos.github.io/ioos_metrics
Project-URL: homepage, https://github.com/ioos/ioos_metrics
Project-URL: repository, https://github.com/ioos/ioos_metrics
Classifier: Programming Language :: Python :: 3 :: Only
Classifier: Programming Language :: Python :: 3.10
Classifier: Programming Language :: Python :: 3.11
Classifier: Programming Language :: Python :: 3.12
Requires-Python: >=3.10
License-File: LICENSE
Requires-Dist: bs4
Requires-Dist: ckanapi
Requires-Dist: fake-useragent
Requires-Dist: geopandas>=0.13.2
Requires-Dist: gliderpy
Requires-Dist: html5lib
Requires-Dist: joblib
Requires-Dist: lxml
Requires-Dist: pandas
Requires-Dist: pdfminer.six
Requires-Dist: pyarrow
Requires-Dist: pyobis
Requires-Dist: requests
Requires-Dist: tenacity
Dynamic: license-file
